goblin_cbm_runner/__init__.py
goblin_cbm_runner/cbm/__init__.py
goblin_cbm_runner/cbm/data_processing/__init__.py
goblin_cbm_runner/cbm/data_processing/default_processing/SC_disturbances.py
goblin_cbm_runner/cbm/data_processing/default_processing/SC_inventory.py
goblin_cbm_runner/cbm/data_processing/default_processing/__init__.py
goblin_cbm_runner/cbm/data_processing/default_processing/cbm_data_factory.py
goblin_cbm_runner/cbm/data_processing/default_processing/create_json.py
goblin_cbm_runner/cbm/data_processing/default_processing/disturnance_utils.py
goblin_cbm_runner/cbm/data_processing/default_processing/transition.py
goblin_cbm_runner/cbm/data_processing/default_processing/yield_curves.py
goblin_cbm_runner/cbm/data_processing/geo_processing/__init__.py
goblin_cbm_runner/cbm/data_processing/geo_processing/catchment_forest_cover.py
goblin_cbm_runner/cbm/data_processing/geo_processing/geo_FM_disturbances.py
goblin_cbm_runner/cbm/data_processing/geo_processing/geo_SC_disturbances.py
goblin_cbm_runner/cbm/data_processing/geo_processing/geo_cbm_data_factory.py
goblin_cbm_runner/cbm/data_processing/geo_processing/geo_create_json.py
goblin_cbm_runner/cbm/data_processing/geo_processing/geo_disturbance_utils.py
goblin_cbm_runner/cbm/data_processing/geo_processing/geo_inventory.py
goblin_cbm_runner/cbm/data_processing/geo_processing/geo_transition.py
goblin_cbm_runner/cbm/methods/__init__.py
goblin_cbm_runner/cbm/methods/cbm_methods.py
goblin_cbm_runner/cbm_validation/__init__.py
goblin_cbm_runner/cbm_validation/validation.py
goblin_cbm_runner/cbm_validation/validation_runner.py
goblin_cbm_runner/configuration_data/__init__.py
goblin_cbm_runner/configuration_data/config.yaml
goblin_cbm_runner/configuration_data/geo_config.yaml
goblin_cbm_runner/database/__init__.py
goblin_cbm_runner/database/cbm_runner_database_0.4.3.db
goblin_cbm_runner/database/ireland_cbm_defaults_v4.db
goblin_cbm_runner/default_runner/__init__.py
goblin_cbm_runner-0.5.0.dist-info/LICENSE
goblin_cbm_runner-0.5.0.dist-info/METADATA
goblin_cbm_runner-0.5.0.dist-info/WHEEL
goblin_cbm_runner-0.5.0.dist-info/RECORD
