Metadata-Version: 2.1
Name: goblin_cbm_runner
Version: 0.5.0
Summary: An interface between the CBM CFS3, libcbm_py, model and the GOBLIN model.
License: MIT
Author: Colm Duffy
Requires-Python: >=3.9,<4.0
Classifier: License :: OSI Approved :: MIT License
Classifier: Programming Language :: Python :: 3
Classifier: Programming Language :: Python :: 3.9
Classifier: Programming Language :: Python :: 3.10
Classifier: Programming Language :: Python :: 3.11
Classifier: Programming Language :: Python :: 3.12
Requires-Dist: catchment_data_api (>=0.1.0,<0.2.0)
Requires-Dist: libcbm (==2.6.6)
Requires-Dist: numpy (>=1.25.0,<2.0.0)
Requires-Dist: pandas (==2.1.4)
Requires-Dist: pyyaml
Requires-Dist: sqlalchemy (>=1.4.0,<2.0.0)
